{"Antibounce":false,"Autoclt":true,"Banner_Flag":0,"Banner_Item":0,"FastSpin":false,"Fastdrp":false,"Fastpull":false,"Fasttsh":false,"HideChat":false,"HideOther":false,"Last_lQuest":"","Spam_Delay":2,"Spam_Text":"Eating ","_drt":false,"achievements":[],"admin":0,"ances":9212,"awaystatus":false,"b_a":0,"b_b":"","b_i":0,"b_l":1,"b_lvl":1,"b_p":0,"b_r":"","b_ra":0,"b_s":0,"b_t":0,"b_w":0,"back":11050,"bank_c":0,"bankfixd":0,"bans":[],"bb":false,"bb_lvl":5,"bb_p":[5],"bb_xp":1223,"blarney":[{"time":0,"world":1},{"time":0,"world":2},{"time":0,"world":3},{"time":0,"world":4},{"time":0,"world":5},{"time":0,"world":6},{"time":0,"world":7},{"time":0,"world":8},{"time":0,"world":9}],"booty_broken":0,"bp":[],"busystatus":false,"bxo":0,"bxoost":0,"cc":1,"cheat_ban":0,"cheat_bounce":0,"cheat_collect":0,"cheat_drop":0,"cheat_kick":0,"cheat_pull":0,"cheater":0,"cjump":false,"clm_k":true,"clm_k1":true,"clm_k2":false,"clm_k3":false,"clm_k4":false,"clm_k5":false,"clm_k6":false,"coin":5,"cspeed":false,"d_name":"","date":19619,"dd":0,"dds":0,"dev":0,"dnr":false,"drtt":false,"e_1":4294967295,"e_2":4294967295,"e_3":4294967295,"egg":0,"email":"martenmiller2@gmail.com","face":5228,"farmable":0,"feet":12346,"ff_lvl":0,"ff_p":[],"ff_xp":0,"flagmay":256,"flagset":0,"founder":0,"friends":[],"g4g_1":22,"g4g_10":0,"g4g_11":30,"g4g_12":0,"g4g_13":0,"g4g_14":6000,"g4g_15":6000,"g4g_16":2,"g4g_17":0,"g4g_19":0,"g4g_2":0,"g4g_3":0,"g4g_4":0,"g4g_5":0,"g4g_6":false,"g4g_7":0,"g4g_8":false,"g4g_9":0,"g4g_combine":0,"g4g_daily":false,"g4g_enter":true,"g_lvl":0,"g_p":[],"g_xp":0,"gd":0,"geiger":0,"gems":6093,"ghost":false,"glo":0,"glo_p":[],"gp":0,"gr":[],"gtwl":0,"guild_id":2,"hair":10330,"hand":12242,"home_world":"","hs":0,"i_11818_1":0,"i_11818_2":0,"inv":[{"c":1,"i":18},{"c":1,"i":32},{"c":1,"i":6336},{"c":2,"i":3494},{"c":43,"i":542},{"c":64,"i":998},{"c":22,"i":3478},{"c":22,"i":3480},{"c":1,"i":5480},{"c":34,"i":1766},{"c":1,"i":10330},{"c":1,"i":12346},{"c":1,"i":12406},{"c":1,"i":13322},{"c":84,"i":2574},{"c":20,"i":3482},{"c":39,"i":3484},{"c":58,"i":242},{"c":66,"i":3488},{"c":20,"i":3490},{"c":175,"i":3564},{"c":1,"i":12868},{"c":101,"i":2590},{"c":36,"i":2010},{"c":1,"i":12242},{"c":21,"i":7450},{"c":200,"i":1098},{"c":1,"i":13478},{"c":1,"i":13480},{"c":1,"i":13482},{"c":1,"i":13484},{"c":5,"i":1898},{"c":1,"i":6896},{"c":1,"i":12892},{"c":1,"i":13712},{"c":64,"i":5034},{"c":200,"i":1094},{"c":200,"i":1096},{"c":1,"i":1968},{"c":200,"i":1058},{"c":1,"i":2204},{"c":200,"i":3870},{"c":1,"i":1216},{"c":174,"i":202},{"c":156,"i":858},{"c":2,"i":2580},{"c":1,"i":11050},{"c":1,"i":13632},{"c":1,"i":999},{"c":18,"i":3486},{"c":18,"i":3492},{"c":146,"i":728},{"c":146,"i":6400},{"c":182,"i":2586},{"c":0,"i":0},{"c":35,"i":382},{"c":47,"i":1684},{"c":0,"i":0},{"c":2,"i":2274},{"c":38,"i":8994},{"c":0,"i":0},{"c":0,"i":0},{"c":49,"i":8204},{"c":56,"i":8262},{"c":0,"i":0},{"c":0,"i":0},{"c":191,"i":192},{"c":0,"i":0},{"c":4,"i":10154},{"c":6,"i":1002},{"c":28,"i":1048},{"c":3,"i":7860},{"c":29,"i":60},{"c":6,"i":682},{"c":0,"i":0},{"c":1,"i":5228},{"c":0,"i":0},{"c":1,"i":9212},{"c":1,"i":1760},{"c":0,"i":0},{"c":0,"i":0},{"c":0,"i":0},{"c":0,"i":0},{"c":0,"i":0},{"c":0,"i":0},{"c":0,"i":0},{"c":0,"i":0},{"c":0,"i":0},{"c":0,"i":0},{"c":0,"i":0},{"c":0,"i":0},{"c":0,"i":0},{"c":0,"i":0},{"c":0,"i":0},{"c":0,"i":0},{"c":0,"i":0},{"c":0,"i":0},{"c":0,"i":0},{"c":0,"i":0},{"c":0,"i":0},{"c":0,"i":0},{"c":0,"i":0},{"c":0,"i":0},{"c":0,"i":0},{"c":0,"i":0},{"c":0,"i":0},{"c":0,"i":0},{"c":0,"i":0},{"c":0,"i":0},{"c":0,"i":0},{"c":0,"i":0},{"c":0,"i":0},{"c":0,"i":0},{"c":0,"i":0},{"c":0,"i":0},{"c":0,"i":0},{"c":0,"i":0},{"c":0,"i":0},{"c":0,"i":0},{"c":0,"i":0},{"c":0,"i":0},{"c":0,"i":0},{"c":0,"i":0},{"c":0,"i":0},{"c":0,"i":0},{"c":0,"i":0},{"c":0,"i":0}],"invis":false,"ip":"87.119.182.202","kit":280,"kit_p":5010,"lQuest_Active":false,"lQuest_Prog":0,"lQuest_Step":1,"last_worlds":[{"name":"START"},{"name":"SETH"},{"name":"SPEND"},{"name":"M"},{"name":"BFGLINKS"},{"name":"G4G"},{"name":"BFG"},{"name":"REALMS"},{"name":"LOVE"},{"name":"SHOP"},{"name":"LINKS"}],"legend":false,"level":19,"lo":"9/22/2022 16:37:23","lvl125":false,"lvl_p":[10,11,12,13,14,15,16,17,18,19],"m_b":"","m_h":0,"m_r":"","mac":"02:00:00:00:00:00","mask":1216,"mds":0,"mer":false,"mk_p":false,"mk_w":false,"mod":0,"modname":"`0MrFrost","mst":0,"n":1,"name":"MrFrost","necklace":13632,"note":"","ok":0,"onpatrol":false,"onstatus":false,"owner":0,"p_7":0,"p_d1":0,"p_d2":false,"p_d3":false,"p_lvl":0,"p_p":[],"p_xp":0,"pants":13480,"pass":"Marten1234","pid":"4","playmods":[],"playtime":25641,"punch":11220,"radio":0,"rb":0,"rc_aura1":768,"rc_aura2":2048,"rc_aura_on1":1,"rc_aura_on2":1,"rc_closed1":0,"rc_closed2":1,"rc_col1":4294967295,"rc_col2":4294967295,"rc_collar_on1":1,"rc_collar_on2":1,"rc_cp1":4294967295,"rc_cp2":4294967295,"rc_delay_on":0,"rc_move1":1,"rc_move2":1,"rid":"01F30DD7675BDF1B08141ABFC1A9038D","roleIcon":6,"roleSkin":6,"rw_closed1":0,"rw_closed2":0,"rw_delay_on":1,"rw_mat1":4096,"rw_mat2":32768,"rw_met_b1":255,"rw_met_b2":255,"rw_met_g1":255,"rw_met_g2":255,"rw_met_r1":255,"rw_met_r2":255,"rw_opened_on1":0,"rw_opened_on2":0,"rw_stamp1":1,"rw_stamp2":0,"rw_tr1":2048,"rw_trail_on1":1,"rw_trail_on2":1,"rw_wg_b1":255,"rw_wg_b2":255,"rw_wg_g1":255,"rw_wg_g2":255,"rw_wg_r1":255,"rw_wg_r2":255,"s_lvl":0,"s_xp":0,"sd":0,"sgt":17,"shirt":13478,"show_location":true,"show_notifications":true,"skin":-2104114177,"skl":0,"su1":0,"su2":0,"superdev":0,"supp":0,"surg_p":[],"t_h":["`9You traded [26 Wiggly Worm, 62 Fire Essence, 2 Money Aura and 10 Ride'O'Gold] with `1Car`9 in `2BFG`9 and received [nothing] `0at 15:20 on 09/22."],"t_lvl":0,"t_p":[],"t_xp":127,"tk":0,"tut_br":true,"tut_bu":true,"tut_crw":true,"tut_lo":true,"tut_pl":true,"tut_sb":true,"tut_sp":false,"vid":"","vip":0,"w_d":22,"w_w":8,"wk":"NONE0","worlds_owned":[{"name":"SEEDS"},{"name":"BUYGUILD"},{"name":"REALMS"},{"name":"BUYXWING"},{"name":"BGL"},{"name":"SPEND"},{"name":"G4G"},{"name":"LINKS"}],"xp":4649}
