{"Antibounce":false,"Autoclt":true,"Banner_Flag":0,"Banner_Item":0,"FastSpin":false,"Fastdrp":false,"Fastpull":false,"Fasttsh":false,"HideChat":false,"HideOther":false,"Last_lQuest":"","Spam_Delay":3,"Spam_Text":"`cBest Server","_drt":false,"achievements":[],"admin":0,"ances":0,"awaystatus":false,"b_a":0,"b_b":"","b_i":0,"b_l":1,"b_lvl":1,"b_p":0,"b_r":"","b_ra":0,"b_s":0,"b_t":0,"b_w":0,"back":0,"bank_c":0,"bankfixd":0,"bans":[],"bb":false,"bb_lvl":5,"bb_p":[],"bb_xp":2002,"blarney":[{"time":0,"world":1},{"time":0,"world":2},{"time":0,"world":3},{"time":0,"world":4},{"time":0,"world":5},{"time":0,"world":6},{"time":0,"world":7},{"time":0,"world":8},{"time":0,"world":9}],"booty_broken":2,"bp":[],"busystatus":false,"bxo":0,"bxoost":0,"cc":1,"cheat_ban":0,"cheat_bounce":0,"cheat_collect":0,"cheat_drop":0,"cheat_kick":0,"cheat_pull":0,"cheater":0,"cjump":false,"clm_k":false,"clm_k1":false,"clm_k2":false,"clm_k3":false,"clm_k4":false,"clm_k5":false,"clm_k6":false,"coin":0,"cspeed":false,"d_name":"","date":19618,"dd":0,"dds":0,"dev":0,"dnr":false,"drtt":false,"e_1":4294967295,"e_2":4294967295,"e_3":4294967295,"egg":0,"email":"ee.ee@gmail.com","face":13476,"farmable":0,"feet":13482,"ff_lvl":0,"ff_p":[],"ff_xp":0,"flagmay":256,"flagset":0,"founder":0,"friends":[],"g4g_1":27,"g4g_10":0,"g4g_11":30,"g4g_12":0,"g4g_13":0,"g4g_14":6000,"g4g_15":6000,"g4g_16":0,"g4g_17":0,"g4g_19":0,"g4g_2":0,"g4g_3":0,"g4g_4":0,"g4g_5":0,"g4g_6":false,"g4g_7":0,"g4g_8":false,"g4g_9":0,"g4g_combine":0,"g4g_daily":false,"g4g_enter":true,"g_lvl":0,"g_p":[],"g_xp":0,"gd":0,"geiger":0,"gems":1967745,"ghost":false,"glo":0,"glo_p":[],"gp":0,"gr":[],"gtwl":0,"guild_id":0,"hair":13474,"hand":5480,"home_world":"","hs":0,"i_11818_1":0,"i_11818_2":0,"inv":[{"c":1,"i":18},{"c":1,"i":32},{"c":1,"i":6336},{"c":1,"i":4812},{"c":1,"i":11068},{"c":1,"i":11684},{"c":8,"i":4584},{"c":1,"i":818},{"c":1,"i":5480},{"c":2,"i":3396},{"c":96,"i":543},{"c":1,"i":9336},{"c":11,"i":2574},{"c":1,"i":8592},{"c":1,"i":13474},{"c":1,"i":6308},{"c":2,"i":3702},{"c":1,"i":7824},{"c":1,"i":5652},{"c":3,"i":2914},{"c":1,"i":5644},{"c":1,"i":7830},{"c":54,"i":4585},{"c":4,"i":242},{"c":1,"i":13476},{"c":58,"i":527},{"c":10,"i":526},{"c":1,"i":5045},{"c":4,"i":9732},{"c":27,"i":341},{"c":78,"i":340},{"c":1,"i":892},{"c":1,"i":13478},{"c":3,"i":5044},{"c":3,"i":5024},{"c":2,"i":5030},{"c":1,"i":13480},{"c":1,"i":13482},{"c":1,"i":13484},{"c":3,"i":10778},{"c":2,"i":1664},{"c":2,"i":1668},{"c":1,"i":1670},{"c":1,"i":10754},{"c":3,"i":2874},{"c":2,"i":10782},{"c":3,"i":11046},{"c":2,"i":8590},{"c":3,"i":1666},{"c":1,"i":8618},{"c":1,"i":8614},{"c":3,"i":6310},{"c":2,"i":4814},{"c":3,"i":3764},{"c":3,"i":3700},{"c":1,"i":9746},{"c":1,"i":4816},{"c":5,"i":4400},{"c":1,"i":4822},{"c":1,"i":4818},{"c":1,"i":2872},{"c":1,"i":11040},{"c":3,"i":6322},{"c":2,"i":3698},{"c":2,"i":1676},{"c":2,"i":11042},{"c":2,"i":842},{"c":1,"i":2868},{"c":1,"i":2864},{"c":5,"i":3404},{"c":1,"i":3398},{"c":1,"i":5640},{"c":0,"i":0},{"c":0,"i":0},{"c":0,"i":0},{"c":0,"i":0},{"c":0,"i":0},{"c":0,"i":0},{"c":0,"i":0},{"c":0,"i":0},{"c":0,"i":0},{"c":0,"i":0},{"c":0,"i":0},{"c":0,"i":0},{"c":0,"i":0},{"c":0,"i":0},{"c":0,"i":0},{"c":0,"i":0},{"c":0,"i":0},{"c":0,"i":0},{"c":0,"i":0},{"c":0,"i":0},{"c":0,"i":0},{"c":0,"i":0},{"c":0,"i":0},{"c":0,"i":0},{"c":0,"i":0}],"invis":false,"ip":"84.231.210.148","kit":0,"kit_p":5010,"lQuest_Active":false,"lQuest_Prog":0,"lQuest_Step":1,"last_worlds":[{"name":"1"},{"name":"TOWN"},{"name":"2"},{"name":"SETSSSSS"},{"name":"SETS"},{"name":"SHOPASDASD"},{"name":"SHOP"},{"name":"SET"},{"name":"X"},{"name":"CAR"},{"name":"BFG"}],"legend":false,"level":24,"lo":"9/27/2022 2:43:26","lvl125":false,"lvl_p":[10],"m_b":"","m_h":0,"m_r":"","mac":"d4:5b:45:2b:4a:eb","mask":2872,"mds":0,"mer":false,"mk_p":false,"mk_w":false,"mod":0,"modname":"`0Repe","mst":0,"n":1,"name":"Repe","necklace":0,"note":"","ok":0,"onpatrol":false,"onstatus":false,"owner":0,"p_7":0,"p_d1":0,"p_d2":false,"p_d3":false,"p_lvl":0,"p_p":[],"p_xp":0,"pants":13480,"pass":"Epska123.","pid":"0,1,1","playmods":[],"playtime":30106,"punch":19816,"radio":0,"rb":0,"rc_aura1":768,"rc_aura2":2048,"rc_aura_on1":1,"rc_aura_on2":1,"rc_closed1":0,"rc_closed2":1,"rc_col1":4294967295,"rc_col2":4294967295,"rc_collar_on1":1,"rc_collar_on2":1,"rc_cp1":4294967295,"rc_cp2":4294967295,"rc_delay_on":0,"rc_move1":1,"rc_move2":1,"rid":"01A62688050F0D07055E080B0D328EC8","roleIcon":6,"roleSkin":6,"rw_closed1":0,"rw_closed2":0,"rw_delay_on":1,"rw_mat1":4096,"rw_mat2":32768,"rw_met_b1":255,"rw_met_b2":255,"rw_met_g1":255,"rw_met_g2":255,"rw_met_r1":255,"rw_met_r2":255,"rw_opened_on1":0,"rw_opened_on2":0,"rw_stamp1":1,"rw_stamp2":0,"rw_tr1":2048,"rw_trail_on1":1,"rw_trail_on2":1,"rw_wg_b1":255,"rw_wg_b2":255,"rw_wg_g1":255,"rw_wg_g2":255,"rw_wg_r1":255,"rw_wg_r2":255,"s_lvl":0,"s_xp":0,"sd":0,"sgt":23,"shirt":13478,"show_location":true,"show_notifications":true,"skin":-2104114177,"skl":0,"su1":0,"su2":0,"superdev":0,"supp":0,"surg_p":[],"t_h":[],"t_lvl":0,"t_p":[],"t_xp":57,"tk":0,"tut_br":true,"tut_bu":true,"tut_crw":true,"tut_lo":true,"tut_pl":true,"tut_sb":true,"tut_sp":false,"vid":"","vip":0,"w_d":18,"w_w":5,"wk":"E9ECE18CA04EC396D842BCE7786CAC73","worlds_owned":[{"name":"1"},{"name":"X"},{"name":"2"}],"xp":5497}
