{"all_access":false,"coleader_access":false,"coleader_elder_access":false,"guild_description":"Vrom Vrom","guild_level":4,"guild_logs":[{"date":1695500604,"display_id":6,"info":"`$Joji`` `wwas invited by`` `$Car``"},{"date":1695552941,"display_id":6,"info":"`$mhm`` `wwas invited by`` `$Car``"},{"date":1695552944,"display_id":5948,"info":"`$mhm`` `wjoined the guild"},{"date":1695761953,"display_id":6,"info":"`$Repe`` `wwas invited by`` `$Car``"},{"date":1695761956,"display_id":5948,"info":"`$Repe`` `wjoined the guild"},{"date":1695762757,"display_id":484,"info":"`$Car`` `2promoted `$Repe`` `oto Elder"},{"date":1695762764,"display_id":484,"info":"`$Car`` `2promoted `$Repe`` `oto Co-Leader"},{"date":1695842045,"display_id":6,"info":"`$alfa`` `wwas invited by`` `$Car``"},{"date":1695842051,"display_id":5948,"info":"`$alfa`` `wjoined the guild"},{"date":1695842068,"display_id":484,"info":"`$Car`` `2promoted `$alfa`` `oto Elder"}],"guild_mascot":[0,2196],"guild_members":[{"last_online":1695870831,"member_name":"Car","public_location":true,"role_id":3,"show_notifications":true},{"last_online":1695559917,"member_name":"mhm","public_location":true,"role_id":0,"show_notifications":true},{"last_online":1695873004,"member_name":"Repe","public_location":true,"role_id":2,"show_notifications":true},{"last_online":1695892586,"member_name":"alfa","public_location":true,"role_id":1,"show_notifications":true}],"guild_name":"Car","guild_world":"7","guild_xp":1506604,"unlocked_mascot":1}
